foliant/config/alt_structure/__init__.py
foliant/config/alt_structure/alt_structure.py
foliant/config/alt_structure/generate.py
foliant/preprocessors/alt_structure.py
foliantcontrib.alt_structure-0.2.1.dist-info/LICENSE
foliantcontrib.alt_structure-0.2.1.dist-info/METADATA
foliantcontrib.alt_structure-0.2.1.dist-info/WHEEL
foliantcontrib.alt_structure-0.2.1.dist-info/top_level.txt
foliantcontrib.alt_structure-0.2.1.dist-info/RECORD
