Metadata-Version: 2.1
Name: foliantcontrib.alt-structure
Version: 0.2.1
Summary: Extension for Foliant documentation tool which generatesalternative chapters structure.
Home-page: https://github.com/foliant-docs/foliantcontrib.alt_structure
Author: Daniil Minukhin
Author-email: ddddsa@gmail.com
License: MIT
Platform: any
Classifier: Development Status :: 5 - Production/Stable
Classifier: Environment :: Console
Classifier: Intended Audience :: Developers
Classifier: License :: OSI Approved :: MIT License
Classifier: Operating System :: OS Independent
Classifier: Programming Language :: Python
Classifier: Topic :: Documentation
Classifier: Topic :: Utilities
Requires-Dist: foliant (>=1.0.4)
Requires-Dist: foliantcontrib.meta (>=1.3)
Requires-Dist: foliantcontrib.utils (>=1.0.2)
